adrv/__init__.py
adrv/bridge.py
adrv/exceptions.py
adrv/models.py
adrv/utils/parser.py
adrv/utils/units.py
adrv-2.0.0.dist-info/LICENSE
adrv-2.0.0.dist-info/METADATA
adrv-2.0.0.dist-info/WHEEL
adrv-2.0.0.dist-info/RECORD
